tickforge_client/__init__.py
tickforge_client/api/__init__.py
tickforge_client/api/auth_api.py
tickforge_client/api/builds_api.py
tickforge_client/api/db_api.py
tickforge_client/api/default_api.py
tickforge_client/api/git_api.py
tickforge_client/api/github_api.py
tickforge_client/api/jobs_api.py
tickforge_client/api/metrics_api.py
tickforge_client/api/redirects_api.py
tickforge_client/api/slack_api.py
tickforge_client/api/workspaces_api.py
tickforge_client/api_client.py
tickforge_client/api_response.py
tickforge_client/configuration.py
tickforge_client/exceptions.py
tickforge_client/models/__init__.py
tickforge_client/models/always_active.py
tickforge_client/models/author_name.py
tickforge_client/models/backup.py
tickforge_client/models/base_user.py
tickforge_client/models/batch_id.py
tickforge_client/models/body_bump_api_workspaces_bump_post.py
tickforge_client/models/body_bump_app_api_workspaces_app_name_bump_post.py
tickforge_client/models/body_qadeploy_api_workspaces_qadeploy_post.py
tickforge_client/models/body_qadestroy_api_workspaces_qadestroy_post.py
tickforge_client/models/branch.py
tickforge_client/models/build_schema.py
tickforge_client/models/cluster.py
tickforge_client/models/code_metric_blob_payload.py
tickforge_client/models/code_metric_blob_response.py
tickforge_client/models/copy_db_payload.py
tickforge_client/models/create_backup_response.py
tickforge_client/models/create_build_payload.py
tickforge_client/models/create_metric_payload.py
tickforge_client/models/create_workspace_payload.py
tickforge_client/models/deleted.py
tickforge_client/models/display_name.py
tickforge_client/models/email.py
tickforge_client/models/error.py
tickforge_client/models/first_name.py
tickforge_client/models/http_validation_error.py
tickforge_client/models/image32.py
tickforge_client/models/is_admin.py
tickforge_client/models/is_app_user.py
tickforge_client/models/is_bot.py
tickforge_client/models/is_email_confirmed.py
tickforge_client/models/is_owner.py
tickforge_client-2.1.0.dist-info/METADATA
tickforge_client-2.1.0.dist-info/WHEEL
tickforge_client-2.1.0.dist-info/RECORD
