Metadata-Version: 2.1
Name: tickforge_client
Version: 2.1.0
Summary: Tickforge API
Home-page: https://github.com/uptick/tickforge
License: NoLicense
Keywords: OpenAPI,OpenAPI-Generator,Tickforge API
Author: William Chu
Author-email: william.chu@uptickhq.com
Requires-Python: >=3.9,<4.0
Classifier: License :: Other/Proprietary License
Classifier: Programming Language :: Python :: 3
Classifier: Programming Language :: Python :: 3.9
Classifier: Programming Language :: Python :: 3.10
Classifier: Programming Language :: Python :: 3.11
Classifier: Programming Language :: Python :: 3.12
Requires-Dist: boto3
Requires-Dist: pydantic (<3)
Requires-Dist: python-dateutil (>=2.8.2)
Requires-Dist: typing-extensions (>=4.7.1)
Requires-Dist: urllib3 (<3.0.0)
Project-URL: Repository, https://github.com/uptick/tickforge
